setup.py
gb_distributions_plots/Binomialdistribution.py
gb_distributions_plots/Gaussiandistribution.py
gb_distributions_plots/Generaldistribution.py
gb_distributions_plots/__init__.py
gb_distributions_plots.egg-info/PKG-INFO
gb_distributions_plots.egg-info/SOURCES.txt
gb_distributions_plots.egg-info/dependency_links.txt
gb_distributions_plots.egg-info/not-zip-safe
gb_distributions_plots.egg-info/top_level.txt