Metadata-Version: 1.0
Name: gb-distributions-plots
Version: 1.0
Summary: Gaussian and Binomial distributions
Home-page: UNKNOWN
Author: Kaustubh Katkar
Author-email: UNKNOWN
License: UNKNOWN
Platform: UNKNOWN
